datatypes_timex_expression/__init__.py
datatypes_timex_expression/date_range.py
datatypes_timex_expression/resolution.py
datatypes_timex_expression/time.py
datatypes_timex_expression/time_range.py
datatypes_timex_expression/timex.py
datatypes_timex_expression/timex_constants.py
datatypes_timex_expression/timex_constraints_helper.py
datatypes_timex_expression/timex_convert.py
datatypes_timex_expression/timex_creator.py
datatypes_timex_expression/timex_date_helpers.py
datatypes_timex_expression/timex_format.py
datatypes_timex_expression/timex_helpers.py
datatypes_timex_expression/timex_inference.py
datatypes_timex_expression/timex_parsing.py
datatypes_timex_expression/timex_range.py
datatypes_timex_expression/timex_range_resolver.py
datatypes_timex_expression/timex_regex.py
datatypes_timex_expression/timex_relative_convert.py
datatypes_timex_expression/timex_resolver.py
datatypes_timex_expression/timex_set.py
datatypes_timex_expression/timex_value.py
datatypes_timex_expression/english/__init__.py
datatypes_timex_expression/english/english_timex_convert.py
datatypes_timex_expression/english/english_timex_relative_convert.py
datatypes_timex_expression/english/timex_constants.py
datatypes_timex_expression-1.0.2a2.dist-info/METADATA
datatypes_timex_expression-1.0.2a2.dist-info/WHEEL
datatypes_timex_expression-1.0.2a2.dist-info/top_level.txt
datatypes_timex_expression-1.0.2a2.dist-info/RECORD
